LICENSE.txt
MANIFEST.in
setup.cfg
setup.py
mobbage/__init__.py
mobbage.egg-info/PKG-INFO
mobbage.egg-info/SOURCES.txt
mobbage.egg-info/dependency_links.txt
mobbage.egg-info/entry_points.txt
mobbage.egg-info/requires.txt
mobbage.egg-info/top_level.txt