Metadata-Version: 1.1
Name: mobbage
Version: 0.2
Summary: A HTTP stress test and benchmark tool
Home-page: https://github.com/redfin/mobbage
Author: Eric Schwimmer
Author-email: git@nerdvana.org
License: Apache 2.0
Keywords: http http/2 benchmark stress load test
Platform: UNKNOWN
Classifier: Development Status :: 5 - Production/Stable
Classifier: Intended Audience :: System Administrators
Classifier: Topic :: System :: Benchmark
Classifier: License :: OSI Approved :: Apache Software License
Classifier: Programming Language :: Python :: 2
Classifier: Programming Language :: Python :: 2.6
Classifier: Programming Language :: Python :: 2.7
Classifier: Programming Language :: Python :: 3
Classifier: Programming Language :: Python :: 3.3
Classifier: Programming Language :: Python :: 3.4
Classifier: Programming Language :: Python :: 3.5
